benchmark/__init__.py
benchmark/benchmark.py
benchmark/hit_rate.py
benchmark/mean_average_precision.py
benchmark/mean_reciprocal_rank.py
benchmark/normalized_dcg.py
benchmark/precision.py
benchmark/recall.py
recsys_metrics/__init__.py
recsys_metrics/alpha_normalized_dcg.py
recsys_metrics/beyond_accuracy_report.py
recsys_metrics/catalog_coverage.py
recsys_metrics/distributional_coverage.py
recsys_metrics/expected_popularity_complement.py
recsys_metrics/hit_rate.py
recsys_metrics/mean_average_precision.py
recsys_metrics/mean_interlist_diversity.py
recsys_metrics/mean_reciprocal_rank.py
recsys_metrics/normalized_dcg.py
recsys_metrics/precision.py
recsys_metrics/rank_report.py
recsys_metrics/recall.py
recsys_metrics/serendipity.py
recsys_metrics/utils.py
recsys_metrics-0.0.4.dist-info/METADATA
recsys_metrics-0.0.4.dist-info/WHEEL
recsys_metrics-0.0.4.dist-info/top_level.txt
recsys_metrics-0.0.4.dist-info/RECORD
