Metadata-Version: 2.1
Name: recsys-metrics
Version: 0.0.4
Summary: An efficient PyTorch implementation of the evaluation metrics in recommender systems.
Home-page: https://github.com/zuoxingdong/recsys_metrics
Author: Xingdong Zuo
Keywords: pytorch,metrics,machine learning,deep learning,recsys,recommender systems,information retrieval
Classifier: Environment :: Console
Classifier: Natural Language :: English
Classifier: Intended Audience :: Developers
Classifier: Topic :: Scientific/Engineering :: Artificial Intelligence
Classifier: Topic :: Scientific/Engineering :: Information Analysis
Classifier: Operating System :: OS Independent
Classifier: Programming Language :: Python :: 3
Classifier: Programming Language :: Python :: 3.7
Classifier: Programming Language :: Python :: 3.8
Classifier: Programming Language :: Python :: 3.9
Classifier: Programming Language :: Python :: 3.10
Requires-Python: >=3.7
Requires-Dist: numpy (>=1.17.2)
Requires-Dist: torch (>=1.3.1)
